README.rst
setup.py
jujuclient/__init__.py
jujuclient/connector.py
jujuclient/environment.py
jujuclient/exc.py
jujuclient/facades.py
jujuclient/rpc.py
jujuclient/utils.py
jujuclient/watch.py
jujuclient.egg-info/PKG-INFO
jujuclient.egg-info/SOURCES.txt
jujuclient.egg-info/dependency_links.txt
jujuclient.egg-info/requires.txt
jujuclient.egg-info/top_level.txt
jujuclient/juju1/__init__.py
jujuclient/juju1/connector.py
jujuclient/juju1/environment.py
jujuclient/juju1/facades.py
jujuclient/juju1/rpc.py
jujuclient/juju1/watch.py
jujuclient/juju2/__init__.py
jujuclient/juju2/connector.py
jujuclient/juju2/environment.py
jujuclient/juju2/facades.py
jujuclient/juju2/rpc.py
jujuclient/juju2/watch.py