Metadata-Version: 1.1
Name: jujuclient
Version: 0.54.0
Summary: A juju-core/gojuju simple synchronous python api client.
Home-page: http://juju.ubuntu.com
Author: Kapil Thangavelu
Author-email: kapil.foss@gmail.com
License: UNKNOWN
Platform: UNKNOWN
Classifier: Development Status :: 4 - Beta
Classifier: Programming Language :: Python
Classifier: Topic :: Internet
Classifier: Topic :: Software Development :: Libraries :: Python Modules
Classifier: License :: OSI Approved :: GNU Library or Lesser General Public License (LGPL)
Classifier: Intended Audience :: Developers
